azure_translator_python3/__init__.py
azure_translator_python3/errors.py
azure_translator_python3-0.0.3.dist-info/METADATA
azure_translator_python3-0.0.3.dist-info/RECORD
azure_translator_python3-0.0.3.dist-info/WHEEL
azure_translator_python3-0.0.3.dist-info/top_level.txt
